fabricflow/__init__.py
fabricflow/log_utils.py
fabricflow/auth/__init__.py
fabricflow/auth/provider.py
fabricflow/core/__init__.py
fabricflow/core/capacities.py
fabricflow/core/connections.py
fabricflow/core/utils.py
fabricflow/core/items/__init__.py
fabricflow/core/items/manager.py
fabricflow/core/items/types.py
fabricflow/core/items/utils.py
fabricflow/core/workspaces/__init__.py
fabricflow/core/workspaces/manager.py
fabricflow/core/workspaces/utils.py
fabricflow/pipeline/__init__.py
fabricflow/pipeline/executor.py
fabricflow/pipeline/utils.py
fabricflow/pipeline/activities/__init__.py
fabricflow/pipeline/activities/base.py
fabricflow/pipeline/activities/copy/__init__.py
fabricflow/pipeline/activities/copy/copy.py
fabricflow/pipeline/activities/copy/executor.py
fabricflow/pipeline/activities/lookup/__init__.py
fabricflow/pipeline/activities/lookup/executor.py
fabricflow/pipeline/activities/lookup/lookup.py
fabricflow/pipeline/sinks/__init__.py
fabricflow/pipeline/sinks/base.py
fabricflow/pipeline/sinks/lakehouse_files.py
fabricflow/pipeline/sinks/lakehouse_table.py
fabricflow/pipeline/sinks/parquet_file.py
fabricflow/pipeline/sinks/types.py
fabricflow/pipeline/sources/__init__.py
fabricflow/pipeline/sources/base.py
fabricflow/pipeline/sources/file_system.py
fabricflow/pipeline/sources/google_big_query.py
fabricflow/pipeline/sources/postgresql.py
fabricflow/pipeline/sources/sql_server.py
fabricflow/pipeline/sources/types.py
fabricflow/pipeline/templates/__init__.py
fabricflow/pipeline/templates/templates.py
fabricflow/pipeline/templates/definitions/CopyFilesToLakehouse.json
fabricflow/pipeline/templates/definitions/CopyGoogleBigQueryToLakehouseTable.json
fabricflow/pipeline/templates/definitions/CopyGoogleBigQueryToParquetFile.json
fabricflow/pipeline/templates/definitions/CopyPostgreSQLToLakehouseTable.json
fabricflow/pipeline/templates/definitions/CopyPostgreSQLToParquetFile.json
fabricflow/pipeline/templates/definitions/CopySQLServerToLakehouseTable.json
fabricflow-0.1.5.dist-info/licenses/LICENSE
fabricflow-0.1.5.dist-info/METADATA
fabricflow-0.1.5.dist-info/WHEEL
fabricflow-0.1.5.dist-info/top_level.txt
fabricflow-0.1.5.dist-info/RECORD
