Metadata-Version: 2.4
Name: fabricflow
Version: 0.1.5
Summary: A code-first approach for MS Fabric data pipelines and ETL.
Author: Parth Lad
License-Expression: MIT
Project-URL: Homepage, https://github.com/ladparth/fabricflow
Project-URL: Repository, https://github.com/ladparth/fabricflow
Project-URL: Issues, https://github.com/ladparth/fabricflow/issues
Project-URL: Changelog, https://github.com/ladparth/fabricflow/blob/main/CHANGELOG.md
Keywords: data,pipeline,ETL,Microsoft Fabric,data engineering,dataOps,data factory pipelines
Classifier: Development Status :: 4 - Beta
Classifier: Intended Audience :: Developers
Classifier: Programming Language :: Python :: 3 :: Only
Classifier: Programming Language :: Python :: 3.11
Classifier: Programming Language :: Python :: 3.12
Classifier: Topic :: Software Development :: Libraries
Classifier: Topic :: Software Development :: Libraries :: Python Modules
Classifier: Topic :: Database
Requires-Python: >=3.10
License-File: LICENSE
Requires-Dist: semantic-link-sempy>=0.8.0
Provides-Extra: dev
Requires-Dist: pytest; extra == "dev"
Dynamic: license-file
